langtojson/__init__.py
langtojson/cli.py
langtojson/langtojson.py
langtojson-0.1.3.dist-info/AUTHORS.rst
langtojson-0.1.3.dist-info/LICENSE
langtojson-0.1.3.dist-info/METADATA
langtojson-0.1.3.dist-info/WHEEL
langtojson-0.1.3.dist-info/entry_points.txt
langtojson-0.1.3.dist-info/top_level.txt
langtojson-0.1.3.dist-info/RECORD
