Metadata-Version: 2.1
Name: langtojson
Version: 0.1.3
Summary: Tool to convert .lang files to JSON
Home-page: https://github.com/Ars2014/langtojson
Author: Arslan Sakhapov
Author-email: arslan.sakhapov@yandex.ru
License: MIT license
Keywords: langtojson
Platform: UNKNOWN
Classifier: Development Status :: 2 - Pre-Alpha
Classifier: Intended Audience :: Developers
Classifier: License :: OSI Approved :: MIT License
Classifier: Natural Language :: English
Classifier: Programming Language :: Python :: 3
Classifier: Programming Language :: Python :: 3.6
Classifier: Programming Language :: Python :: 3.7
Classifier: Programming Language :: Python :: 3.8
Requires-Python: >=3.5
Requires-Dist: Click (>=7.0)
